fish_databricks_jobs/__init__.py
fish_databricks_jobs/cli.py
fish_databricks_jobs/config.py
fish_databricks_jobs/services/__init__.py
fish_databricks_jobs/services/jobs.py
fish_databricks_jobs/services/permissions.py
fish_databricks_jobs/services/version.py
fish_databricks_jobs-0.7.18.dist-info/METADATA
fish_databricks_jobs-0.7.18.dist-info/WHEEL
fish_databricks_jobs-0.7.18.dist-info/entry_points.txt
fish_databricks_jobs-0.7.18.dist-info/RECORD
