Metadata-Version: 2.1
Name: fish-databricks-jobs
Version: 0.7.18
Summary: cli and sdk to manage Jobs in Databricks
Home-page: https://github.com/firstim/fish-databricks-jobs
Author: Tim Chen
Author-email: firstim@gmail.com
Requires-Python: >=3.7,<4.0
Classifier: Programming Language :: Python :: 3
Classifier: Programming Language :: Python :: 3.7
Classifier: Programming Language :: Python :: 3.8
Classifier: Programming Language :: Python :: 3.9
Classifier: Programming Language :: Python :: 3.10
Classifier: Programming Language :: Python :: 3.11
Classifier: Programming Language :: Python :: 3.12
Requires-Dist: databricks-cli (>=0.17.0,<0.18.0)
Requires-Dist: tabulate (>=0.9.0,<0.10.0)
Requires-Dist: typer[all] (>=0.7.0,<0.8.0)
